[ {
  "entityIndex" : "1_entity25665",
  "entityUrl" : "http://dbpedia.org/resource/Rajpur,_Baroda",
  "dboClass" : "dbo:City",
  "properties" : {
    "dbp:isoCode" : [ "http://dbpedia.org/resource/ISO_3166-2:IN" ]
  },
  "words" : [ "Rajput", "Rajpur", "Mansinhji", "lord", "bank", "state", "Fatehsinhji", "last", "princely", "Thakur", "Jaladhar", "Saheb", "Mahisagar", "history", ",", ".", "Baroda", "associated", "Indian", "located", "river", "family", "royal", "Mahadevaji", "Shree" ],
  "adjectives" : [ "last", "princely", "Indian", "located" ],
  "nouns" : [ "bank", "lord", "state", "river", "history", "family", "royal" ],
  "text" : "Rajpur, Baroda was an Indian princely state located on the bank of river Mahisagar. Thakur Saheb Shree Mansinhji Fatehsinhji was the last Thakur Saheb of Rajpur. The history of the Rajput royal family is associated with lord Jaladhar Mahadevaji."
} ]