[ {
  "entityIndex" : "1_entity14597",
  "entityUrl" : "http://dbpedia.org/resource/Ciudad_Guadalupe_Victoria",
  "dboClass" : "dbo:City",
  "properties" : {
    "dbp:precipitationColour" : [ "green" ]
  },
  "words" : [ "Guadalupe", "Municipality", "city", "Victoria", "2010", "Ciudad", ",", ".", "population", "seat", "Durango", "north-western", "Mexico", "state", "16,506" ],
  "adjectives" : [ "north-western" ],
  "nouns" : [ "seat", "city", "state", "population" ],
  "text" : "Ciudad Guadalupe Victoria  is a city and seat of Guadalupe Victoria Municipality, in the state of Durango, north-western Mexico. As of 2010, the city of Guadalupe Victoria had a population of 16,506."
}, {
  "entityIndex" : "2_entity17326",
  "entityUrl" : "http://dbpedia.org/resource/Girdharpur",
  "dboClass" : "dbo:City",
  "properties" : {
    "dbp:precipitationColour" : [ "green" ]
  },
  "words" : [ "``", "46", "-LRB-", "away", "27", "28", "E.", "51.60", "N", "Bareilly", "गिरधरपुर", "Pradesh", "lies", "state", "village", "Girdharpur", "Uttar", "79", "37", "within", "&", "Highway", "'", "coordinates", ",", ".", "گردھرپر", "°", "3", "State", "district", "kilometers", "-RRB-", "Indian", "42" ],
  "adjectives" : [ "Indian" ],
  "nouns" : [ "district", "state", "village" ],
  "text" : "Girdharpur( गिरधरपुर, گردھرپر ) is a village in Bareilly district of the Indian state of Uttar Pradesh. It is 3 kilometers away from State Highway 37 and lies within the coordinates 28°42'51.60\"N & 79°27'46\"E."
}, {
  "entityIndex" : "3_entity24859",
  "entityUrl" : "http://dbpedia.org/resource/Palin,_Arunachal_Pradesh",
  "dboClass" : "dbo:City",
  "properties" : {
    "dbp:precipitationColour" : [ "green" ]
  },
  "words" : [ "small", "28.15285", "Daadi", "MLA", "-LRB-", "latitude", "according", "August-2016", "Name", "5816", "current", "headquarter", "Pradesh", "Located", "station", "Arunachal", "longitude", "Nyishi", "town", "Tagar", "Takam", "2001", ",", ".", "population", "hill", "94.12288", "Pario", "constituency", "Palin", "tribe", "district", "census", "-RRB-", "inhabited", "Kra" ],
  "adjectives" : [ "small", "current", "headquarter" ],
  "nouns" : [ "hill", "MLA", "town", "constituency", "tribe", "district", "latitude", "census", "station", "August-2016", "longitude", "population" ],
  "text" : "Palin is a small hill station town and the headquarter of Kra Daadi district in Arunachal Pradesh. It is inhabited by Nyishi tribe of Arunachal Pradesh. Located at latitude of 28.15285 and a longitude 94.12288, it has a population of 5816 according to 2001 census. Name of current MLA (August-2016) of Palin constituency is  Takam Tagar (Pario)."
}, {
  "entityIndex" : "4_entity23371",
  "entityUrl" : "http://dbpedia.org/resource/New_Palin",
  "dboClass" : "dbo:City",
  "properties" : {
    "dbp:precipitationColour" : [ "green" ]
  },
  "words" : [ "New", "largest", "28.15285", "hillstation", "Dadi", "Nyishi", "town", "Latitude", ",", "Longitude", ".", "94.12288", "Palin", "Pradesh", "tribe", "district", "located", "inhabited", "Kra", "Arunachal" ],
  "adjectives" : [ "located" ],
  "nouns" : [ "hillstation", "town", "tribe", "district" ],
  "text" : "New Palin is a hillstation town located in the Kra Dadi district of Arunachal Pradesh. It is the largest town in the district. It is inhabited by Nyishi tribe of Arunachal Pradesh. It is located at Latitude 28.15285, Longitude 94.12288. It has a population of 5816 according to 2001 census."
}, {
  "entityIndex" : "5_entity19385",
  "entityUrl" : "http://dbpedia.org/resource/Kamshet",
  "dboClass" : "dbo:City",
  "properties" : {
    "dbp:precipitationColour" : [ "green" ]
  },
  "words" : [ "small", "45", "accessible", "surrounded", "-LRB-", "beauty", "Lonavala", "Maval", "attract", "main", "scenic", "Mumbai", "around", "110", "Kamshet", "reeds", "road", "Bombay", "thatch", "70", "immense", "state", "Maharashtra", "twin", "Khandala", "area", "km", "villages", "16", "built", "rail", "City", "stations", ",", "people", ".", "India", "home", "market", "hill", "traditional", "district", "-RRB-", "located", "Pune", "style", "60", "mud" ],
  "adjectives" : [ "small", "accessible", "traditional", "located", "immense", "main", "scenic", "twin" ],
  "nouns" : [ "area", "km", "beauty", "rail", "home", "market", "hill", "road", "thatch", "district", "style", "state", "mud" ],
  "text" : "Kamshet is located in Pune district in the state of Maharashtra, India, 110 km from Mumbai City, and 45 km from Pune in Pune district. It is 16 km from the twin hill stations of Khandala and Lonavala and is accessible by road and rail from Mumbai (Bombay) and Pune. Kamshet is surrounded by immense scenic beauty, and is home to small villages that are built in the traditional style (with mud, thatch and reeds).Maval is the main market of area and attract people from around 60 to 70 villages. On every Tuesday, a vegetable market is set up where the people from Kamshet and neighbouring areas visit."
} ]