[ {
  "entityIndex" : "1_entity12610",
  "entityUrl" : "http://dbpedia.org/resource/Jack_Ellis_(actor)",
  "dboClass" : "dbo:Actor",
  "properties" : {
    "dbp:patner" : [ "claire Bejanin" ]
  },
  "words" : [ "``", "TV", "Bookmaker", "brothers", "officer", "John", "ITV", "portrayal", "Ellis", "theatre", "Coronation", "appeared", "children", "Street", "Theo", "prison", "divorced", "Harry", "wife", "Alice", "director", ",", "Girls", ".", "former", "4", "Mason", "London", "-RRB-", "Robin", "soap", "June", "Christine", "-LRB-", "best", "two", "School", "known", "older", "Jack", "1955", "''", "Highgate", "Bad", "television", "born", "also", "Jim", "Kavanagh", "actor", "English", "educated", "Stuart", "series", "villainous", "Fenner", "Peter" ],
  "adjectives" : [ "English", "villainous", "former" ],
  "nouns" : [ "theatre", "actor", "TV", "television", "officer", "series", "wife", "director", "portrayal", "prison", "soap" ],
  "text" : "John Stuart \"Jack\" Ellis (born 4 June 1955 in London) is an English theatre and television actor best known for his portrayal of villainous prison officer Jim Fenner in the TV series Bad Girls. He has also appeared in ITV soap Coronation Street as Bookmaker Harry Mason. He and his former wife Christine Kavanagh, from whom he is now divorced, have two children, Theo and Alice. He was educated at Highgate School as were his older brothers Robin Ellis, also an actor, and the director Peter Ellis."
} ]