[ {
  "entityIndex" : "1_entity14820",
  "entityUrl" : "http://dbpedia.org/resource/Sun_Feifei",
  "dboClass" : "dbo:Actor",
  "properties" : {
    "dbo:wikiPageDisambiguates" : [ "http://dbpedia.org/resource/Sun_Feifei_(actress)" ]
  },
  "words" : [ ],
  "adjectives" : [ ],
  "nouns" : [ ],
  "text" : ""
}, {
  "entityIndex" : "2_entity15021",
  "entityUrl" : "http://dbpedia.org/resource/Shinpei_Takagi",
  "dboClass" : "dbo:Actor",
  "properties" : {
    "dbo:wikiPageDisambiguates" : [ "http://dbpedia.org/resource/Shinpei_Takagi_(actor,_born_1902)", "http://dbpedia.org/resource/Shinpei_Takagi_(actor,_born_1985)" ]
  },
  "words" : [ ],
  "adjectives" : [ ],
  "nouns" : [ ],
  "text" : ""
}, {
  "entityIndex" : "3_entity15224",
  "entityUrl" : "http://dbpedia.org/resource/Tim_Matthews",
  "dboClass" : "dbo:Actor",
  "properties" : {
    "dbo:wikiPageDisambiguates" : [ "http://dbpedia.org/resource/Tim_Matthews_(actor)", "http://dbpedia.org/resource/Tim_Matthews_(athlete)", "http://dbpedia.org/resource/Tim_Matthews_(bishop)", "http://dbpedia.org/resource/Tim_Matthews_(racing_driver)" ]
  },
  "words" : [ ],
  "adjectives" : [ ],
  "nouns" : [ ],
  "text" : ""
}, {
  "entityIndex" : "4_entity15360",
  "entityUrl" : "http://dbpedia.org/resource/Vincent_Wong",
  "dboClass" : "dbo:Actor",
  "properties" : {
    "dbo:wikiPageDisambiguates" : [ "http://dbpedia.org/resource/Vincent_Wong_(Hong_Kong_actor)", "http://dbpedia.org/resource/Vincent_Wong_(UK_actor)" ]
  },
  "words" : [ ],
  "adjectives" : [ ],
  "nouns" : [ ],
  "text" : ""
}, {
  "entityIndex" : "5_entity15361",
  "entityUrl" : "http://dbpedia.org/resource/Victor_Brooks",
  "dboClass" : "dbo:Actor",
  "properties" : {
    "dbo:wikiPageDisambiguates" : [ "http://dbpedia.org/resource/Victor_Brooks_(actor)", "http://dbpedia.org/resource/Victor_Brooks_(athlete)" ]
  },
  "words" : [ ],
  "adjectives" : [ ],
  "nouns" : [ ],
  "text" : ""
}, {
  "entityIndex" : "6_entity13333",
  "entityUrl" : "http://dbpedia.org/resource/Linda_Armstrong",
  "dboClass" : "dbo:Actor",
  "properties" : {
    "dbo:wikiPageDisambiguates" : [ "http://dbpedia.org/resource/Linda_Armstrong_(actress)", "http://dbpedia.org/resource/Linda_Armstrong_(artist)" ]
  },
  "words" : [ ],
  "adjectives" : [ ],
  "nouns" : [ ],
  "text" : ""
}, {
  "entityIndex" : "7_entity13458",
  "entityUrl" : "http://dbpedia.org/resource/Lily_Ho",
  "dboClass" : "dbo:Actor",
  "properties" : {
    "dbo:wikiPageDisambiguates" : [ "http://dbpedia.org/resource/Lily_Ho_Li_Li", "http://dbpedia.org/resource/Lily_Ho_Ngo_Yee" ]
  },
  "words" : [ ],
  "adjectives" : [ ],
  "nouns" : [ ],
  "text" : ""
}, {
  "entityIndex" : "8_entity12328",
  "entityUrl" : "http://dbpedia.org/resource/Hiroshi_Kawaguchi",
  "dboClass" : "dbo:Actor",
  "properties" : {
    "dbo:wikiPageDisambiguates" : [ "http://dbpedia.org/resource/Hiroshi_Kawaguchi_(actor)", "http://dbpedia.org/resource/Hiroshi_Kawaguchi_(composer)" ]
  },
  "words" : [ ],
  "adjectives" : [ ],
  "nouns" : [ ],
  "text" : ""
}, {
  "entityIndex" : "9_entity10791",
  "entityUrl" : "http://dbpedia.org/resource/Alan_Mak",
  "dboClass" : "dbo:Actor",
  "properties" : {
    "dbo:wikiPageDisambiguates" : [ "http://dbpedia.org/resource/Alan_Mak_(director)", "http://dbpedia.org/resource/Alan_Mak_(politician)" ]
  },
  "words" : [ ],
  "adjectives" : [ ],
  "nouns" : [ ],
  "text" : ""
}, {
  "entityIndex" : "10_entity10872",
  "entityUrl" : "http://dbpedia.org/resource/Angela_Clarke",
  "dboClass" : "dbo:Actor",
  "properties" : {
    "dbo:wikiPageDisambiguates" : [ "http://dbpedia.org/resource/Angela_Clarke_(American_actress)", "http://dbpedia.org/resource/Angela_Clarke_(British_actress)", "http://dbpedia.org/resource/Angela_Clarke_(volleyball)" ]
  },
  "words" : [ ],
  "adjectives" : [ ],
  "nouns" : [ ],
  "text" : ""
}, {
  "entityIndex" : "11_entity11046",
  "entityUrl" : "http://dbpedia.org/resource/Andrew_Yuen",
  "dboClass" : "dbo:Actor",
  "properties" : {
    "dbo:wikiPageDisambiguates" : [ "http://dbpedia.org/resource/Andrew_Yuen_Chi-lok", "http://dbpedia.org/resource/Andrew_Yuen_Man-fai", "http://dbpedia.org/resource/Andrew_Yuen_Man-kit" ]
  },
  "words" : [ ],
  "adjectives" : [ ],
  "nouns" : [ ],
  "text" : ""
}, {
  "entityIndex" : "12_entity13538",
  "entityUrl" : "http://dbpedia.org/resource/Miho_Takagi",
  "dboClass" : "dbo:Actor",
  "properties" : {
    "dbo:wikiPageDisambiguates" : [ "http://dbpedia.org/resource/Miho_Takagi_(speed_skater)", "http://dbpedia.org/resource/Miho_Takagi_(actress)" ]
  },
  "words" : [ ],
  "adjectives" : [ ],
  "nouns" : [ ],
  "text" : ""
}, {
  "entityIndex" : "13_entity13557",
  "entityUrl" : "http://dbpedia.org/resource/Masahiro_Kobayashi",
  "dboClass" : "dbo:Actor",
  "properties" : {
    "dbo:wikiPageDisambiguates" : [ "http://dbpedia.org/resource/Masahiro_Kobayashi_(actor)", "http://dbpedia.org/resource/Masahiro_Kobayashi_(director)" ]
  },
  "words" : [ ],
  "adjectives" : [ ],
  "nouns" : [ ],
  "text" : ""
}, {
  "entityIndex" : "14_entity12774",
  "entityUrl" : "http://dbpedia.org/resource/Jin_Sha",
  "dboClass" : "dbo:Actor",
  "properties" : {
    "dbo:wikiPageDisambiguates" : [ "http://dbpedia.org/resource/Jin_Sha_(poet)", "http://dbpedia.org/resource/Jin_Sha_(singer)" ]
  },
  "words" : [ ],
  "adjectives" : [ ],
  "nouns" : [ ],
  "text" : ""
} ]